README.md
setup.py
atbot/__init__.py
atbot/tgchat.py
atbot/tgmessage.py
atbot/tgtype.py
atbot/tgupdate.py
atbot/tguser.py
atbot.egg-info/PKG-INFO
atbot.egg-info/SOURCES.txt
atbot.egg-info/dependency_links.txt
atbot.egg-info/requires.txt
atbot.egg-info/top_level.txt