Metadata-Version: 2.1
Name: atbot
Version: 1.0.0
Summary: Asynchronous Telegram Bot API
Home-page: https://github.com/naim94a/atbot
Author: Naim A.
Author-email: naim@abda.nl
License: MIT
Project-URL: Issues, https://github.com/naim94a/atbot/issues
Project-URL: Pull Requests, https://github.com/naim94a/atbot/pulls
Platform: UNKNOWN
Classifier: Intended Audience :: Developers
Classifier: License :: OSI Approved :: MIT License
Classifier: Operating System :: OS Independent
Classifier: Programming Language :: Python :: 3
Requires-Python: >=3.5.3
